smth/__init__.py
smth/unreal_file.py
testpackages32-0.2.7.dist-info/METADATA
testpackages32-0.2.7.dist-info/WHEEL
testpackages32-0.2.7.dist-info/top_level.txt
testpackages32-0.2.7.dist-info/RECORD
