Metadata-Version: 2.1
Name: testpackages32
Version: 0.2.7
Summary: lulw
Home-page: UNKNOWN
Author: Igor Simagin
Author-email: igorsim35@gmail.com
License: UNKNOWN
Platform: UNKNOWN
Requires-Dist: numpy
Requires-Dist: pandas
